pypkgpack/__init__.py
pypkgpack/bundle.py
pypkgpack/importer.py
pypkgpack-0.4.0.dist-info/entry_points.txt
pypkgpack-0.4.0.dist-info/LICENSE
pypkgpack-0.4.0.dist-info/WHEEL
pypkgpack-0.4.0.dist-info/METADATA
pypkgpack-0.4.0.dist-info/RECORD
