Metadata-Version: 2.1
Name: pypkgpack
Version: 0.4.0
Summary: Bundling your Python project into a single Python file.
Author: thautwarm
Author-email: twshere@outlook.com
Requires-Python: >=3.7,<4.0
Classifier: Programming Language :: Python :: 3
Classifier: Programming Language :: Python :: 3.10
Classifier: Programming Language :: Python :: 3.7
Classifier: Programming Language :: Python :: 3.8
Classifier: Programming Language :: Python :: 3.9
Requires-Dist: ast-compat (>=0.11.1,<0.12.0)
Requires-Dist: wisepy2 (>=1.3,<2.0)
